LDpred-1.0.11.data/scripts/run.py
ldpred/LD_pruning_thres.py
ldpred/LDpred_fast.py
ldpred/LDpred_gibbs.py
ldpred/LDpred_inf.py
ldpred/__init__.py
ldpred/__main__.py
ldpred/coord_genotypes.py
ldpred/ld.py
ldpred/plinkfiles.py
ldpred/plots.py
ldpred/reporting.py
ldpred/run.py
ldpred/sum_stats_parsers.py
ldpred/util.py
ldpred/validate.py
ldpred/reference/hm3_sids.txt.gz
ldpred/reference/long-range-ld-price-2008hg38.txt
tests/__init__.py
tests/test.py
tests/test_data/sim1_0_ss.txt
tests/test_data/sim1_0_test.bed
tests/test_data/sim1_0_test.bim
tests/test_data/sim1_0_test.fam
tests/test_data/sim1_parameters.json
tests/test_data/sim2_0_ss.txt
tests/test_data/sim2_0_test.bed
tests/test_data/sim2_0_test.bim
tests/test_data/sim2_0_test.fam
tests/test_data/sim2_parameters.json
tests/test_data/sim3_0_ss.txt
tests/test_data/sim3_0_test.bed
tests/test_data/sim3_0_test.bim
tests/test_data/sim3_0_test.fam
tests/test_data/sim3_parameters.json
tests/test_data/sim4_0_ss.txt
tests/test_data/sim4_0_test.bed
tests/test_data/sim4_0_test.bim
tests/test_data/sim4_0_test.fam
tests/test_data/sim4_parameters.json
tests/test_data/sim5_0_ss.txt
tests/test_data/sim5_0_test.bed
tests/test_data/sim5_0_test.bim
tests/test_data/sim5_0_test.fam
tests/test_data/sim5_parameters.json
tests/test_data/goldens/golden.coord.hdf5
tests/test_data/goldens/golden.coord0.hdf5
tests/test_data/goldens/golden_LDpred-inf.txt
tests/test_data/goldens/golden_LDpred_p1.0000e-03.txt
tests/test_data/goldens/golden_P+T_r0.20_p1.0000e-03.txt
tests/test_data/goldens/golden_inf_LDpred-inf.txt
tests/test_data/goldens/golden_inf_ldradius100.pkl.gz
tests/test_data/goldens/golden_ldradius100.pkl.gz
tests/test_data/goldens/golden_mix1_prs_1_0.summary.txt
tests/test_data/goldens/golden_mix1_prs_2_0.summary.txt
tests/test_data/goldens/golden_mix1_prs_3_0.summary.txt
tests/test_data/goldens/golden_mix1_prs_4_0.summary.txt
tests/test_data/goldens/golden_mix1_prs_5_0.summary.txt
tests/test_data/goldens/golden_mix2_prs_1_0.summary.txt
LDpred-1.0.11.dist-info/LICENSE.txt
LDpred-1.0.11.dist-info/METADATA
LDpred-1.0.11.dist-info/WHEEL
LDpred-1.0.11.dist-info/entry_points.txt
LDpred-1.0.11.dist-info/top_level.txt
LDpred-1.0.11.dist-info/RECORD
