Metadata-Version: 2.1
Name: LDpred
Version: 1.0.11
Summary: A Python package that adjusts GWAS summary statistics for the effects of linkage disequilibrium (LD)
Home-page: https://github.com/ldpred
Author: Bjarni J Vilhjalmsson
Author-email: bjarni.vilhjalmsson@gmail.com
License: MIT
Keywords: Polygenic Risk Scores,GWAS,Linkage Disequilibrium,Risk Prediction
Platform: UNKNOWN
Classifier: Development Status :: 4 - Beta
Classifier: Intended Audience :: Science/Research
Classifier: Topic :: Software Development :: Build Tools
Classifier: License :: OSI Approved :: MIT License
Classifier: Programming Language :: Python :: 2.7
Classifier: Programming Language :: Python :: 3.7
Requires-Dist: h5py
Requires-Dist: scipy
Requires-Dist: plinkio
